g2pw/__init__.py
g2pw/api.py
g2pw/bert-base-chinese_s2t_dict.txt
g2pw/bopomofo_to_pinyin_wo_tune_dict.json
g2pw/char_bopomofo_dict.json
g2pw/dataset.py
g2pw/module.py
g2pw/utils.py
g2pw-0.1.1.dist-info/LICENCE
g2pw-0.1.1.dist-info/METADATA
g2pw-0.1.1.dist-info/WHEEL
g2pw-0.1.1.dist-info/top_level.txt
g2pw-0.1.1.dist-info/RECORD
