Metadata-Version: 2.1
Name: g2pw
Version: 0.1.1
Summary: g2pW
Home-page: https://github.com/GitYCC/g2pW
Author: Yi-Chang Chen
Author-email: ycc.tw.email@gmail.com
License: Apache License 2.0
Platform: UNKNOWN
Classifier: Development Status :: 4 - Beta
Classifier: Intended Audience :: Developers
Classifier: Intended Audience :: Science/Research
Classifier: License :: OSI Approved :: Apache Software License
Classifier: Operating System :: OS Independent
Classifier: Programming Language :: Python :: 3
Classifier: Programming Language :: Python :: 3.6
Classifier: Programming Language :: Python :: 3.7
Requires-Python: >=3.6
Requires-Dist: tqdm
Requires-Dist: onnxruntime
Requires-Dist: transformers
